MANIFEST.in
README.rst
setup.py
tgapp_youtubevideo.egg-info/PKG-INFO
tgapp_youtubevideo.egg-info/SOURCES.txt
tgapp_youtubevideo.egg-info/dependency_links.txt
tgapp_youtubevideo.egg-info/entry_points.txt
tgapp_youtubevideo.egg-info/not-zip-safe
tgapp_youtubevideo.egg-info/paster_plugins.txt
tgapp_youtubevideo.egg-info/requires.txt
tgapp_youtubevideo.egg-info/top_level.txt
youtubevideo/__init__.py
youtubevideo/bootstrap.py
youtubevideo/helpers.py
youtubevideo/partials.py
youtubevideo/controllers/__init__.py
youtubevideo/controllers/root.py
youtubevideo/lib/__init__.py
youtubevideo/model/__init__.py
youtubevideo/model/models.py
youtubevideo/public/__init__.py
youtubevideo/public/css/style.css
youtubevideo/public/images/star.png
youtubevideo/templates/__init__.py
youtubevideo/templates/index.html
youtubevideo/templates/video.html
youtubevideo/templates/videogallery_partial.html