Metadata-Version: 1.0
Name: tgapp-youtubevideo
Version: 0.0.3
Summary: Provides a pluggable youtube video gallery in TurboGears applications and provides a way to filter them by tags.
Home-page: UNKNOWN
Author: Alessandro Molina
Author-email: alessandro.molina@axant.it
License: UNKNOWN
Keywords: turbogears2.application
Platform: UNKNOWN
